Pattern/__init__.py
Candlestick-0.0.5.dist-info/LICENSE
Candlestick-0.0.5.dist-info/METADATA
Candlestick-0.0.5.dist-info/WHEEL
Candlestick-0.0.5.dist-info/top_level.txt
Candlestick-0.0.5.dist-info/RECORD
