Metadata-Version: 2.1
Name: Candlestick
Version: 0.0.5
Summary: A package for finding the candlestick pattern from OHLC data
Home-page: UNKNOWN
Author: Harshad Bhirud
Author-email: harshad.coder@gmail.com
License: UNKNOWN
Platform: UNKNOWN
Classifier: Programming Language :: Python :: 3
Classifier: License :: OSI Approved :: MIT License
Classifier: Operating System :: OS Independent
Requires-Python: >=3.6
License-File: LICENSE
Requires-Dist: numpy (>1)
Requires-Dist: pandas (>1)
